{
    "code": 200,
    "msg": "success",
    "data": [
        {
            "id": "f648dfd6-227a-4466-af19-fc20fb737fd8",
            "rate": "MONTH",
            "rateTime": "202204",
            "valueFactMon": "7843015.5671",
            "growthOnMonth": -2.9867532,
            "valueFactYear": "28320475.3439",
            "growthOnYear": 3.1657143,
            "appItemName": "工业用电量"
        },
        {
            "id": "b1d7c579-3f55-4533-a303-36e13a428aaf",
            "rate": "MONTH",
            "rateTime": "202205",
            "valueFactMon": "7911309.177499999",
            "growthOnMonth": -5.691818,
            "valueFactYear": "36231784.52139999",
            "growthOnYear": 1.0566233,
            "appItemName": "工业用电量"
        },
        {
            "id": "45052809-b88c-4e21-be6c-e8c09c380364",
            "rate": "MONTH",
            "rateTime": "202206",
            "valueFactMon": "8100880.997",
            "growthOnMonth": -3.9597402,
            "valueFactYear": "44332665.468600005",
            "growthOnYear": -0.033116885,
            "appItemName": "工业用电量"
        },
        {
            "id": "edce330d-a8d7-41f8-9430-767f649f03ac",
            "rate": "MONTH",
            "rateTime": "202207",
            "valueFactMon": "8767096.177400002",
            "growthOnMonth": -2.470909,
            "valueFactYear": "53099761.676000014",
            "growthOnYear": -0.5138961,
            "appItemName": "工业用电量"
        },
        {
            "id": "43bce6ed-53ef-4d73-b732-78be531f762a",
            "rate": "MONTH",
            "rateTime": "202208",
            "valueFactMon": "8627610.7968",
            "growthOnMonth": -6.2987013,
            "valueFactYear": "61727602.46119995",
            "growthOnYear": -1.3607792,
            "appItemName": "工业用电量"
        },
        {
            "id": "53ac677d-6ddf-4019-b3e0-5918be9a8b38",
            "rate": "MONTH",
            "rateTime": "202209",
            "valueFactMon": "8289818.856400001",
            "growthOnMonth": -0.7746753,
            "valueFactYear": "70017191.29940002",
            "growthOnYear": -1.3455844,
            "appItemName": "工业用电量"
        },
        {
            "id": "ae4908cb-4ce5-4943-8d49-7944f3a7a1a6",
            "rate": "MONTH",
            "rateTime": "202210",
            "valueFactMon": "8237223.594000002",
            "growthOnMonth": 14.997821,
            "valueFactYear": "78254644.91299999",
            "growthOnYear": 0.001025641,
            "appItemName": "工业用电量"
        },
        {
            "id": "34fe94dd-9b8c-4356-a092-fdcc5e6fc3de",
            "rate": "MONTH",
            "rateTime": "202211",
            "valueFactMon": "8082617.485700001",
            "growthOnMonth": 2.3989744,
            "valueFactYear": "86337262.42870001",
            "growthOnYear": 0.17,
            "appItemName": "工业用电量"
        },
        {
            "id": "667a07f6-9369-4c68-a5e3-da26f599727c",
            "rate": "MONTH",
            "rateTime": "202212",
            "valueFactMon": "8222405.201599999",
            "growthOnMonth": -8.142436,
            "valueFactYear": "94559437.56350002",
            "growthOnYear": -0.76679486,
            "appItemName": "工业用电量"
        },
        {
            "id": "e5b2d32c-bf51-4d4b-a858-ca7bd748a764",
            "rate": "MONTH",
            "rateTime": "202301",
            "valueFactMon": "4314361.9399999995",
            "growthOnMonth": -42.291153,
            "valueFactYear": "4314361.9399999995",
            "growthOnYear": -42.291153,
            "appItemName": "工业用电量"
        },
        {
            "id": "53f83d6d-36e4-46ca-abbf-86c9716969ce",
            "rate": "MONTH",
            "rateTime": "202302",
            "valueFactMon": "7101384.370900001",
            "growthOnMonth": 51.854614,
            "valueFactYear": "11415746.309100004",
            "growthOnYear": -4.2978206,
            "appItemName": "工业用电量"
        },
        {
            "id": "b355949b-1879-4669-8a6f-332c2c084bc5",
            "rate": "MONTH",
            "rateTime": "202303",
            "valueFactMon": "9001724.989999996",
            "growthOnMonth": 3.4033334,
            "valueFactYear": "20417471.269999996",
            "growthOnYear": -0.9896154,
            "appItemName": "工业用电量"
        },
        {
            "id": "1159f496-6a62-4c30-b4bc-8cf0bdfefaa7",
            "rate": "MONTH",
            "rateTime": "202304",
            "valueFactMon": "8463993.318200001",
            "growthOnMonth": 7.8639746,
            "valueFactYear": "28881464.5814",
            "growthOnYear": 1.4396154,
            "appItemName": "工业用电量"
        },
        {
            "id": "fcdaaf2a-b433-4167-8dde-0c5a73f0e4c2",
            "rate": "MONTH",
            "rateTime": "202305",
            "valueFactMon": "8681917.2044",
            "growthOnMonth": 11.430641,
            "valueFactYear": "37563381.78580001",
            "growthOnYear": 3.4379487,
            "appItemName": "工业用电量"
        },
        {
            "id": "b7f04375-6531-4479-be8c-3463c58662d1",
            "rate": "MONTH",
            "rateTime": "202306",
            "valueFactMon": "8897279.217899999",
            "growthOnMonth": 9.878077,
            "valueFactYear": "46460661.00369998",
            "growthOnYear": 4.5489745,
            "appItemName": "工业用电量"
        },
        {
            "id": "0f27a4d5-d9bb-43d7-9b93-a74860410a8e",
            "rate": "MONTH",
            "rateTime": "202307",
            "valueFactMon": "9577649.71",
            "growthOnMonth": 11.193334,
            "valueFactYear": "56038310.760000005",
            "growthOnYear": 5.536154,
            "appItemName": "工业用电量"
        },
        {
            "id": "db0a478b-43be-456d-95da-8cdfaa0e4332",
            "rate": "MONTH",
            "rateTime": "202308",
            "valueFactMon": "9733818.132899996",
            "growthOnMonth": 15.075384,
            "valueFactYear": "65772128.86270003",
            "growthOnYear": 6.7653847,
            "appItemName": "工业用电量"
        },
        {
            "id": "dbe762f8-6fd2-48fe-a9bf-5f0b17ac7167",
            "rate": "MONTH",
            "rateTime": "202309",
            "valueFactMon": null,
            "growthOnMonth": null,
            "valueFactYear": "45456465",
            "growthOnYear": null,
            "appItemName": "工业用电量"
        },
        {
            "id": "fe7ab926-06ac-466e-826e-8905f1e20943",
            "rate": "MONTH",
            "rateTime": "202310",
            "valueFactMon": null,
            "growthOnMonth": null,
            "valueFactYear": null,
            "growthOnYear": null,
            "appItemName": "工业用电量"
        },
        {
            "id": "83c3e66a-d2cb-4640-b77f-fc9067343947",
            "rate": "MONTH",
            "rateTime": "202009",
            "valueFactMon": "6186925.3999999985",
            "growthOnMonth": 10.323947,
            "valueFactYear": "58467077.48000001",
            "growthOnYear": 11.363947,
            "appItemName": "工业用电量"
        },
        {
            "id": "6e411643-bac9-4ed6-9e7e-5582ce961413",
            "rate": "MONTH",
            "rateTime": "202010",
            "valueFactMon": "7396927.1517",
            "growthOnMonth": 21.000658,
            "valueFactYear": "65864004.610400006",
            "growthOnYear": 12.315394,
            "appItemName": null
        },
        {
            "id": "30991107-fe3b-4f82-b64d-08499b32f7c8",
            "rate": "MONTH",
            "rateTime": "202012",
            "valueFactMon": "8731708.202999998",
            "growthOnMonth": 22.519737,
            "valueFactYear": "82486635.81740001",
            "growthOnYear": 14.258289,
            "appItemName": "工业用电量"
        },
        {
            "id": "eb2925e5-6916-4814-9840-610fbf667763",
            "rate": "MONTH",
            "rateTime": "202101",
            "valueFactMon": "7581816.9911",
            "growthOnMonth": 125.460526,
            "valueFactYear": "7581816.9911",
            "growthOnYear": 125.460526,
            "appItemName": "工业用电量"
        },
        {
            "id": "27b32f2e-e7ee-4000-9b83-633497aeeeeb",
            "rate": "MONTH",
            "rateTime": "202102",
            "valueFactMon": "3673869.6422",
            "growthOnMonth": 361.85196,
            "valueFactYear": "11255686.633299993",
            "growthOnYear": 139.76514,
            "appItemName": "工业用电量"
        },
        {
            "id": "2e12fe47-022b-4dc0-a799-eb57c7f720c8",
            "rate": "MONTH",
            "rateTime": "202103",
            "valueFactMon": "8098274.696499995",
            "growthOnMonth": 40.87935,
            "valueFactYear": "19375554.306599993",
            "growthOnYear": 68.902855,
            "appItemName": "工业用电量"
        },
        {
            "id": "a8bc0086-7d06-4e91-95a7-5592c6e9c5eb",
            "rate": "MONTH",
            "rateTime": "202104",
            "valueFactMon": "8161279.210799998",
            "growthOnMonth": 18.532236,
            "valueFactYear": "27536833.517400004",
            "growthOnYear": 46.8325,
            "appItemName": "工业用电量"
        },
        {
            "id": "998ba907-11f0-4695-9778-2ce8cbe4d188",
            "rate": "MONTH",
            "rateTime": "202105",
            "valueFactMon": "8301851.971600004",
            "growthOnMonth": 17.6675,
            "valueFactYear": "35838685.48900002",
            "growthOnYear": 38.483288,
            "appItemName": "工业用电量"
        },
        {
            "id": "cbee41f8-a138-43bd-aa44-d4d21e1412f7",
            "rate": "MONTH",
            "rateTime": "202106",
            "valueFactMon": "8298742.177499997",
            "growthOnMonth": 2.2961843,
            "valueFactYear": "44137427.6665",
            "growthOnYear": 29.418158,
            "appItemName": "工业用电量"
        },
        {
            "id": "08f1c20f-bc56-4e6b-be2f-5173eec8c383",
            "rate": "MONTH",
            "rateTime": "202107",
            "valueFactMon": "8855384.183199996",
            "growthOnMonth": 2.9951315,
            "valueFactYear": "52992811.849700004",
            "growthOnYear": 23.692762,
            "appItemName": "工业用电量"
        },
        {
            "id": "394a377f-7ea3-4a09-ae62-0a80a63b59d8",
            "rate": "MONTH",
            "rateTime": "202108",
            "valueFactMon": "9039066.246099997",
            "growthOnMonth": -4.8210526,
            "valueFactYear": "62031878.09579998",
            "growthOnYear": 18.220526,
            "appItemName": "工业用电量"
        },
        {
            "id": "ea9702f1-e08a-4276-843e-54c7e9c5e7ff",
            "rate": "MONTH",
            "rateTime": "202109",
            "valueFactMon": "8324345.642000001",
            "growthOnMonth": 23.73092,
            "valueFactYear": "70356223.7378",
            "growthOnYear": 20.805395,
            "appItemName": "工业用电量"
        },
        {
            "id": "4c38f639-4d01-450e-8a79-29ea334b6dfb",
            "rate": "MONTH",
            "rateTime": "202110",
            "valueFactMon": "7240829.2639",
            "growthOnMonth": -0.550921,
            "valueFactYear": "77597053.0017",
            "growthOnYear": 18.330921,
            "appItemName": "工业用电量"
        },
        {
            "id": "c5af6bb6-7dd5-486d-9dfe-25b0e2f9fbe7",
            "rate": "MONTH",
            "rateTime": "202111",
            "valueFactMon": "7872937.618399999",
            "growthOnMonth": -0.11473684,
            "valueFactYear": "85469990.6201",
            "growthOnYear": 16.264078,
            "appItemName": "工业用电量"
        },
        {
            "id": "af72cd0d-ff37-43a9-8fad-07c9f54da8d4",
            "rate": "MONTH",
            "rateTime": "202112",
            "valueFactMon": "8797636.989500001",
            "growthOnMonth": 3.9189475,
            "valueFactYear": "94267627.60960002",
            "growthOnYear": 14.803289,
            "appItemName": "工业用电量"
        },
        {
            "id": "b30ecfbe-19db-41c4-81ab-977d8057748b",
            "rate": "MONTH",
            "rateTime": "202201",
            "valueFactMon": "6693704.254",
            "growthOnMonth": -12.157013,
            "valueFactYear": "6693704.254",
            "growthOnYear": -12.157013,
            "appItemName": "工业用电量"
        },
        {
            "id": "966e460a-b72c-4315-8227-13e4258e8be5",
            "rate": "MONTH",
            "rateTime": "202202",
            "valueFactMon": "5069505.840800001",
            "growthOnMonth": 48.27935,
            "valueFactYear": "11763210.094799995",
            "growthOnYear": 3.8862338,
            "appItemName": "工业用电量"
        },
        {
            "id": "5968f962-699e-4767-bd79-dcc5024ab1de",
            "rate": "MONTH",
            "rateTime": "202203",
            "valueFactMon": "8675231.543599997",
            "growthOnMonth": 8.645454,
            "valueFactYear": "20477459.7768",
            "growthOnYear": 5.891039,
            "appItemName": "工业用电量"
        }
    ]
}